ampharos/__init__.py
ampharos/data/abilities.json
ampharos/data/items.json
ampharos/data/moves.json
ampharos/data/pokemon.json
ampharos/data/pokemonabilities.json
ampharos/data/pokemonbasestats.json
ampharos/data/pokemondexentries.json
ampharos/data/pokemonevolutions.json
ampharos/data/pokemonnames.json
ampharos/data/pokemontypes.json
ampharos/search.py
ampharos/setup.py
ampharos/tables.py
ampharos/types.py
ampharos/utils.py
ampharos-3.0.0.dist-info/LICENSE
ampharos-3.0.0.dist-info/METADATA
ampharos-3.0.0.dist-info/WHEEL
ampharos-3.0.0.dist-info/RECORD
